[
    {
        "idString": "165304617",
        "id": 165304617,
        "channelId": 11249217,
        "channelName": "jakenbakeLIVE",
        "chapters": [],
        "chatEmbed": 0,
        "chatFile": null,
        "chatVideoFile": null,
        "created": 1502168321,
        "length": 11592,
        "metadataFile": null,
        "muteList": "",
        "thumbnailUrl": "",
        "title": "Tokyo, Japan - Fake Chipotle in Roppongi - Dinner with new !friends in Shibuya - jnbHey",
        "videoFile": null,
        "vodId": 165304617,
        "chatYoutubeId": "6cNMlL5MLnI",
        "videoYoutubeId": "qOloPNBttJY"
    }
]