[
    {
        "idString": "179316235",
        "id": 179316235,
        "channelId": 11249217,
        "channelName": "jakenbakeLIVE",
        "chapters": [],
        "chatEmbed": 0,
        "chatFile": null,
        "chatVideoFile": null,
        "created": 1507000530,
        "length": 1860,
        "metadataFile": null,
        "muteList": "",
        "thumbnailUrl": "",
        "title": "Tokyo, JPN - Shinjuku and Tsukiji Fish Market w/ !Emi - jnbOnion - [50% off !Sub] - !friends !discord",
        "videoFile": null,
        "vodId": 179316235,
        "videoYoutubeId": "mnEY_OJ-JSo,syQC52X5YNI",
        "chatYoutubeId": "mnEY_OJ-JSo"
    }
]