[
    {
        "idString": "179887121",
        "id": 179887121,
        "channelId": 11249217,
        "channelName": "jakenbakeLIVE",
        "chapters": [],
        "chatEmbed": 0,
        "chatFile": null,
        "chatVideoFile": null,
        "created": 1507213769,
        "length": 3391,
        "metadataFile": null,
        "muteList": "",
        "thumbnailUrl": "",
        "title": "Tokyo, JPN - Thirsty Thursday - [50% off !Sub] - !friends !discord !subgoal",
        "videoFile": null,
        "vodId": 179887121,
        "chatYoutubeId": "WW_IMYMyLUA",
        "videoYoutubeId": "L238nhlrzrk"
    }
]