[
    {
        "idString": "203474717",
        "id": 203474717,
        "channelId": 11249217,
        "channelName": "jakenbakeLIVE",
        "chapters": [],
        "chatEmbed": 0,
        "chatFile": null,
        "chatVideoFile": null,
        "created": 1511379287,
        "length": 479,
        "metadataFile": null,
        "muteList": "",
        "thumbnailUrl": "",
        "title": "LA Day 2 - Breakfast and Gifts for Japanese Friends w/ Dad - LA for Thanksgiving (21-27) - jnbChamp - !discord !wotd !subgoal",
        "videoFile": null,
        "vodId": 203474717,
        "videoYoutubeId": "nC4vlK6QYlA,37O1X7wnqkw",
        "chatYoutubeId": "nC4vlK6QYlA"
    }
]