[
    {
        "idString": "214148028",
        "id": 214148028,
        "channelId": 11249217,
        "channelName": "jakenbakeLIVE",
        "chapters": [],
        "chatEmbed": 0,
        "chatFile": null,
        "chatVideoFile": null,
        "created": 1514732978,
        "length": 16818,
        "metadataFile": null,
        "muteList": "",
        "thumbnailUrl": "",
        "title": "Tokyo, JPN - NYE Shenanigans - Fun w/ !Friends jnbKappa - !discord !subgoal",
        "videoFile": null,
        "vodId": 214148028,
        "chatYoutubeId": "elwXnaSay2o",
        "videoYoutubeId": "iHvFAYPg1ko"
    }
]