[
    {
        "idString": "214719786",
        "id": 214719786,
        "channelId": 11249217,
        "channelName": "jakenbakeLIVE",
        "chapters": [],
        "chatEmbed": 0,
        "chatFile": null,
        "chatVideoFile": null,
        "created": 1514911359,
        "length": 10243,
        "metadataFile": null,
        "muteList": "",
        "thumbnailUrl": "",
        "title": "Taiwan Takeover w/ !Dustin (Day 1) jnbD - Night Walkers - !discord !socials ",
        "videoFile": null,
        "vodId": 214719786,
        "videoYoutubeId": "XrxORCSug0I,vrdDCSawc-8",
        "chatYoutubeId": "XrxORCSug0I"
    }
]