[
    {
        "idString": "225974826",
        "id": 225974826,
        "channelId": 11249217,
        "channelName": "jakenbakeLIVE",
        "chapters": [],
        "chatEmbed": 0,
        "chatFile": null,
        "chatVideoFile": null,
        "created": 1517843219,
        "length": 17,
        "metadataFile": null,
        "muteList": "",
        "thumbnailUrl": "",
        "title": "Tokyo, JPN - I Have the Flu. Short Stream. Noodles. Uganda @ 3,000 Subs  - jnbCry- !discord !socials !subgoal",
        "videoFile": null,
        "vodId": 225974826,
        "chatYoutubeId": "moxkt8bujow",
        "videoYoutubeId": "uckSLfqrpmQ"
    }
]